<?xml version="1.0" encoding="UTF-8"?>
<!DOCTYPE suite SYSTEM "https://testng.org/testng-1.0.dtd">
<suite name="Suite">
  <test thread-count="5" name="DashTest">
    <classes>   
     
        <class name="Dash.clockInToDashboardReservedStation"/> 
        <class name="Dash.clockInAssignToHistoricalStation"/>  	
      	<class name="Dash.ClockinAMSLineOperators"/> 
     	<class name="Dash.ReleaseMTNLAssignToStation"/>
     	<class name="Dash.ReleaseAndSentHome"/>        
      	<class name="Dash.DragAndDrop"/>  
     	<class name="Dash.checkDuplication"/>
      	<class name="Dash.ClockOutFromDashaboardStation"/>
   		<class name="Dash.ClockOutFromUnassignedPanel"/>  
       	  
    </classes>
  </test> <!-- DependentOnCreateClass -->
</suite> <!-- Suite -->
